{
  "list": [
    {
      "ticker": "AAPL",
      "volatility": 2.341893752123966
    },
    {
      "ticker": "MSFT",
      "volatility": 1.4276687139305622
    },
    {
      "ticker": "NVDA",
      "volatility": 1.1699282949035268
    },
    {
      "ticker": "FB",
      "volatility": 0.6340790465609528
    },
    {
      "ticker": "NFLX",
      "volatility": 0.43530567402413317
    },
    {
      "ticker": "GOOGL",
      "volatility": -0.29164546709293615
    }
  ],
  "updated": "2020-09-03T17:15:39.450636"
}