{
  "list": [
    {
      "ticker": "NVDA",
      "volatility": 2.608723322393166
    },
    {
      "ticker": "NFLX",
      "volatility": 1.932365975758933
    },
    {
      "ticker": "MSFT",
      "volatility": 1.8397345729317245
    },
    {
      "ticker": "AAPL",
      "volatility": 1.4655682467059026
    },
    {
      "ticker": "GOOGL",
      "volatility": -0.4597473312591936
    },
    {
      "ticker": "FB",
      "volatility": -0.7087544090922787
    }
  ],
  "updated": "2020-08-05T07:53:11.965742"
}