{
  "list": [
    {
      "ticker": "NFLX",
      "volatility": 5.155803505815123
    },
    {
      "ticker": "NVDA",
      "volatility": 3.6065276671234354
    },
    {
      "ticker": "GOOGL",
      "volatility": 2.2749931998625
    },
    {
      "ticker": "FB",
      "volatility": 2.0725598735394737
    },
    {
      "ticker": "AAPL",
      "volatility": 1.5172878973715547
    },
    {
      "ticker": "MSFT",
      "volatility": 1.470391693988153
    }
  ],
  "updated": "2020-07-10T14:08:40.035282"
}