{
  "list": [
    {
      "ticker": "GOOGL",
      "volatility": 1.0044218496358712
    },
    {
      "ticker": "AAPL",
      "volatility": 0.615190872478163
    },
    {
      "ticker": "NFLX",
      "volatility": 0.5478293718976155
    },
    {
      "ticker": "FB",
      "volatility": 0.364890925146106
    },
    {
      "ticker": "NVDA",
      "volatility": 0.0931165930326514
    },
    {
      "ticker": "MSFT",
      "volatility": 0.08307903979462525
    }
  ],
  "updated": "2020-12-04T15:54:26.396978"
}