{
  "list": [
    {
      "ticker": "NFLX",
      "volatility": 4.176078498164575
    },
    {
      "ticker": "NVDA",
      "volatility": 2.116982543426167
    },
    {
      "ticker": "GOOGL",
      "volatility": 1.5411416832326372
    },
    {
      "ticker": "FB",
      "volatility": 1.3837550812771302
    },
    {
      "ticker": "MSFT",
      "volatility": 0.9732009455789125
    },
    {
      "ticker": "AAPL",
      "volatility": 0.9448586144026967
    }
  ],
  "updated": "2020-07-10T17:58:03.337088"
}