{
  "list": [
    {
      "ticker": "NVDA",
      "volatility": 0.9056307629599962
    },
    {
      "ticker": "FB",
      "volatility": 0.7232239430316602
    },
    {
      "ticker": "MSFT",
      "volatility": 0.6524457617133167
    },
    {
      "ticker": "GOOGL",
      "volatility": 0.5760793539651564
    },
    {
      "ticker": "AAPL",
      "volatility": 0.5681461057289114
    },
    {
      "ticker": "NFLX",
      "volatility": 0.44958576208085427
    }
  ],
  "updated": "2020-11-06T16:14:45.207777"
}